{
  "subjectId": "cpdm",
  "title": "बालमानसशास्त्र व अध्यापनशास्त्र",
  "posts": [
    {
      "id": "post_1",
      "title": "मानसशास्त्र: व्याख्या, उगम आणि आधुनिक स्वरूप",
      "url": "https://www.e-gurumitra.com/2026/02/psychology.html",
      "thumbnail": "",
      "description": "शमानसशास्त्र: व्याख्या, उगम आणि आधुनिक स्वरूप"
    },
    {
      "id": "post_2",
      "title": "बालमानसशास्त्र: स्वरूप, व्याप्ती",
      "url": "https://www.e-gurumitra.com/2026/02/child-psychology.html",
      "thumbnail": "",
      "description": "बालमानसशास्त्र: स्वरूप, व्याप्ती"
    },
    {
      "id": "post_3",
      "title": "शैक्षणिक मानसशास्त्राची ओळख",
      "url": "https://www.e-gurumitra.com/2026/02/educational-psychology.html",
      "thumbnail": "",
      "description": "शैक्षणिक मानसशास्त्राची ओळख"
    },
    {
      "id": "post_4",
      "title": "वर्तन अभ्यासाच्या शास्त्रीय पद्धती",
      "url": "https://www.e-gurumitra.com/2026/02/study-methods.html",
      "thumbnail": "",
      "description": "वर्तन अभ्यासाच्या शास्त्रीय पद्धती"
    },
    {
      "id": "post_5",
      "title": "वाढ आणि विकास",
      "url": "https://www.e-gurumitra.com/2026/02/development.html",
      "thumbnail": "",
      "description": "वाढ आणि विकास"
    },
     {
      "id": "post_6",
      "title": "विकासाच्या अवस्था: शैशवावस्था व बाल्यावस्था",
      "url": "https://www.e-gurumitra.com/2026/02/stages1.html",
      "thumbnail": "",
      "description": "विकासाच्या अवस्था: शैशवावस्था व बाल्यावस्था"
    },
     {
      "id": "post_7",
      "title": "पौगंडावस्था: आव्हाने व मार्गदर्शन",
      "url": "https://www.e-gurumitra.com/2026/02/adolescence.html",
      "thumbnail": "",
      "description": "पौगंडावस्था: आव्हाने व मार्गदर्शन"
    },
     {
      "id": "post_8",
      "title": "विकासाचे सिद्धांत",
      "url": "https://www.e-gurumitra.com/2026/02/developmental-theories.html",
      "thumbnail": "",
      "description": "विकासाचे सिद्धांत"
    },
     {
      "id": "post_9",
      "title": "अनुवंश आणि परिस्थिती",
      "url": "https://www.e-gurumitra.com/2026/02/heredity-vs-environment.html",
      "thumbnail": "",
      "description": "अनुवंश आणि परिस्थिती"
    },
     {
      "id": "post_10",
      "title": "अध्ययन प्रक्रिया : स्वरूप व व्याप्ती",
      "url": "https://www.e-gurumitra.com/2026/02/learning-process.html",
      "thumbnail": "",
      "description": "अध्ययन प्रक्रिया : स्वरूप व व्याप्ती"
    },
     {
      "id": "post_11",
      "title": "अध्ययन वक्र आणि पठारावस्था",
      "url": "https://www.e-gurumitra.com/2026/02/learning-curve-plateau.html",
      "thumbnail": "",
      "description": "अध्ययन वक्र आणि पठारावस्था"
    },
    {
      "id": "post_12",
      "title": "अध्ययन उपपत्ती संकल्पना आणि प्रयत्न-प्रमाद उपपत्ती",
      "url": "https://www.e-gurumitra.com/2026/02/learning-theory.html",
      "thumbnail": "",
      "description": "अध्ययन उपपत्ती संकल्पना आणि प्रयत्न-प्रमाद उपपत्ती"
    },
    {
      "id": "post_13",
      "title": "अभिसंधानाचे दोन प्रमुख प्रकार - अभिजात आणि साधक",
      "url": "https://www.e-gurumitra.com/2026/02/conditioning.html",
      "thumbnail": "",
      "description": "अभिसंधानाचे दोन प्रमुख प्रकार - अभिजात आणि साधक"
    },
    {
      "id": "post_14",
      "title": "सान्निध्य आणि पद्धतशीर वर्तन - साहचर्यवादाची पुढची पायरी",
      "url": "https://www.e-gurumitra.com/2026/02/next-conditioning.html",
      "thumbnail": "",
      "description": "सान्निध्य आणि पद्धतशीर वर्तन - साहचर्यवादाची पुढची पायरी"
    },
    {
      "id": "post_15",
      "title": "ज्ञानात्मक दृष्टिकोन - मर्मदृष्टी आणि क्षेत्रीय उपपत्ती",
      "url": "https://www.e-gurumitra.com/2026/02/cognitive-insight.html",
      "thumbnail": "",
      "description": "ज्ञानात्मक दृष्टिकोन - मर्मदृष्टी आणि क्षेत्रीय उपपत्ती"
    },
    {
      "id": "post_16",
      "title": "अध्ययन अनुदेशन आणि ज्ञानात्मक विकास",
      "url": "https://www.e-gurumitra.com/2026/02/blog-post_23.html",
      "thumbnail": "",
      "description": "अध्ययन अनुदेशन आणि ज्ञानात्मक विकास"
    },
     {
      "id": "post_17",
      "title": "श्रेणीबद्ध आणि संकेत अध्ययन उपपत्ती",
      "url": "https://www.e-gurumitra.com/2026/02/hierarchical-and-sigh-theory.html",
      "thumbnail": "",
      "description": "श्रेणीबद्ध आणि संकेत अध्ययन उपपत्ती"
    },
     {
      "id": "post_18",
      "title": "आधुनिक उपपत्ती - सामाजिक निरीक्षण आणि प्रभुत्व संपादन",
      "url": "https://www.e-gurumitra.com/2026/02/social-and-mastery.html",
      "thumbnail": "",
      "description": "आधुनिक उपपत्ती - सामाजिक निरीक्षण आणि प्रभुत्व संपादन"
    },
    {
      "id": "post_19",
      "title": "आधुनिक उपपत्ती - माहिती प्रक्रियाकरण प्रतिमान",
      "url": "https://www.e-gurumitra.com/2026/02/information-processing-model.html",
      "thumbnail": "",
      "description": "आधुनिक उपपत्ती - माहिती प्रक्रियाकरण प्रतिमान"
    },
    {
      "id": "post_20",
      "title": "अध्ययनावर परिणाम करणारे घटक: अनुवंश आणि परिसर",
      "url": "https://www.e-gurumitra.com/2026/03/heredity-and-environment.html",
      "thumbnail": "",
      "description": "अध्ययनावर परिणाम करणारे घटक: अनुवंश आणि परिसर"
    },
    {
      "id": "post_21",
      "title": "अध्ययनावर परिणाम करणारे घटक - संवेदन आणि अवबोध",
      "url": "https://www.e-gurumitra.com/2026/03/sensation-and-perception.html",
      "thumbnail": "",
      "description": "अध्ययनावर परिणाम करणारे घटक - संवेदन आणि अवबोध"
    },
    {
      "id": "post_22",
      "title": "मानसप्रतिमा, कल्पना आणि विचार प्रक्रिया",
      "url": "https://www.e-gurumitra.com/2026/03/imagery-imagination-and-thinking.html",
      "thumbnail": "",
      "description": "मानसप्रतिमा, कल्पना आणि विचार प्रक्रिया"
    },
    {
      "id": "post_23",
      "title": "अध्ययनावर परिणाम करणारे घटक: स्मृती आणि विस्मरण",
      "url": "https://www.e-gurumitra.com/2026/03/memory-and-forgetting.html",
      "thumbnail": "",
      "description": "अध्ययनावर परिणाम करणारे घटक: स्मृती आणि विस्मरण"
    },
     {
      "id": "post_24",
      "title": "अध्ययनावर परिणाम करणारे घटक: अभिप्रेरणा आणि भावना",
      "url": "https://www.e-gurumitra.com/2026/03/motivation-and-emotion.html",
      "thumbnail": "",
      "description": "अध्ययनावर परिणाम करणारे घटक: अभिप्रेरणा आणि भावना"
    },
     {
      "id": "post_25",
      "title": "अवधान, अभिरुची आणि कल",
      "url": "https://www.e-gurumitra.com/2026/03/attention-interest-and-aptitude.html",
      "thumbnail": "",
      "description": "अवधान, अभिरुची आणि कल"
    },
    {
      "id": "post_26",
      "title": "अध्यापन प्रक्रिया: संकल्पना, स्वरूप आणि उद्दिष्टे",
      "url": "https://www.e-gurumitra.com/2026/03/teaching-process.html",
      "thumbnail": "",
      "description": "अध्यापन प्रक्रिया: संकल्पना, स्वरूप आणि उद्दिष्टे"
    },
    {
      "id": "post_27",
      "title": "प्रभावी अध्यापन: अवस्था, वैशिष्ट्ये आणि तत्त्वे",
      "url": "https://www.e-gurumitra.com/2026/03/teaching-stages.html",
      "thumbnail": "",
      "description": "प्रभावी अध्यापन: अवस्था, वैशिष्ट्ये आणि तत्त्वे"
    },
    {
      "id": "post_28",
      "title": "शिक्षक प्रधान अध्यापन पद्धती",
      "url": "https://www.e-gurumitra.com/2026/03/blog-post.html",
      "thumbnail": "",
      "description": "शिक्षक प्रधान अध्यापन पद्धती"
    },
    {
      "id": "post_29",
      "title": "विद्यार्थी प्रधान आणि आधुनिक अध्यापन पद्धती",
      "url": "https://www.e-gurumitra.com/2026/03/student-centered.html",
      "thumbnail": "",
      "description": "विद्यार्थी प्रधान आणि आधुनिक अध्यापन पद्धतीी"
    },
    {
      "id": "post_30",
      "title": "अध्यापनाची सूत्रे",
      "url": "https://www.e-gurumitra.com/2026/03/maxims-of-teaching.html",
      "thumbnail": "",
      "description": "अध्यापनाची सूत्रे"
    },
    {
      "id": "post_31",
      "title": "आशययुक्त अध्यापन पद्धती",
      "url": "https://www.e-gurumitra.com/2026/03/content-based.html",
      "thumbnail": "",
      "description": "आशययुक्त अध्यापन पद्धती"
    },
    {
      "id": "post_32",
      "title": "अध्यापन प्रतिमाने",
      "url": "https://www.e-gurumitra.com/2026/03/models-of-teaching.html",
      "thumbnail": "",
      "description": "अध्यापन प्रतिमाने"
    },
    {
      "id": "post_33",
      "title": "अध्यापनाची साधने आणि तंत्रज्ञान",
      "url": "https://www.e-gurumitra.com/2026/03/teaching-aids.html",
      "thumbnail": "",
      "description": "अध्यापनाची साधने आणि तंत्रज्ञान"
    },
    {
      "id": "post_34",
      "title": "बुद्धिमत्ता सिद्धांत भाग 1",
      "url": "https://www.e-gurumitra.com/2026/03/intelligence-theories.html",
      "thumbnail": "",
      "description": "बुद्धिमत्ता सिद्धांत भाग 1"
    },
    {
      "id": "post_35",
      "title": "बुद्धिमत्ता सिद्धांत - भाग २",
      "url": "https://www.e-gurumitra.com/2026/03/intelligence-theories_21.html",
      "thumbnail": "",
      "description": "बुद्धिमत्ता सिद्धांत - भाग २"
    },
    {
      "id": "post_36",
      "title": "बुद्धिमत्तेचे मापन",
      "url": "https://www.e-gurumitra.com/2026/03/intelligence-testing.html",
      "thumbnail": "",
      "description": "बुद्धिमत्तेचे मापन"
    },
    {
      "id": "post_37",
      "title": "भावनिक बुद्धिमत्ता (EQ)",
      "url": "https://www.e-gurumitra.com/2026/03/eq.html",
      "thumbnail": "",
      "description": "भावनिक बुद्धिमत्ता (EQ)"
    },
    {
      "id": "post_38",
      "title": "भावनिक बुद्धिमत्ता मापन",
      "url": "https://www.e-gurumitra.com/2026/03/eq_21.html",
      "thumbnail": "",
      "description": "भावनिक बुद्धिमत्ता मापन"
    },
    {
      "id": "post_39",
      "title": "व्यक्तिमत्व - स्वरूप आणि निर्धाराके",
      "url": "https://www.e-gurumitra.com/2026/03/personality.html",
      "thumbnail": "",
      "description": "व्यक्तिमत्व - स्वरूप आणि निर्धाराके"
    },
    {
      "id": "post_40",
      "title": "व्यक्तिमत्व सिद्धांत",
      "url": "https://www.e-gurumitra.com/2026/03/personality-theories.html",
      "thumbnail": "",
      "description": "व्यक्तिमत्व सिद्धांत"
    },
    {
      "id": "post_41",
      "title": "वैयक्तिक भिन्नता",
      "url": "https://www.e-gurumitra.com/2026/03/individual-differences.html",
      "thumbnail": "",
      "description": "वैयक्तिक भिन्नता"
    },
    {
      "id": "post_42",
      "title": "शिक्षकाचे व्यक्तिमत्व",
      "url": "https://www.e-gurumitra.com/2026/03/teacher-personality.html",
      "thumbnail": "",
      "description": "शिक्षकाचे व्यक्तिमत्व"
    },
    {
      "id": "post_43",
      "title": "मानवी चेतसंस्था",
      "url": "https://www.e-gurumitra.com/2026/03/human-nervous-system.html",
      "thumbnail": "",
      "description": "मानवी चेतसंस्था"
    },
    {
      "id": "post_44",
      "title": "मानसिक ताण व संघर्ष",
      "url": "https://www.e-gurumitra.com/2026/03/stress-and-conflict.html",
      "thumbnail": "",
      "description": "मानसिक ताण व संघर्ष"
    },
    {
      "id": "post_45",
      "title": "मानसिक आरोग्य",
      "url": "https://www.e-gurumitra.com/2026/03/mental-health.html",
      "thumbnail": "",
      "description": "मानसिक आरोग्य"
    },
    {
      "id": "post_46",
      "title": "ज्ञानरचनावाद",
      "url": "https://www.e-gurumitra.com/2026/03/constructivism.html",
      "thumbnail": "",
      "description": "ज्ञानरचनावाद"
    },
    {
      "id": "post_47",
      "title": "विशेष गरजा असणारी बालके",
      "url": "https://www.e-gurumitra.com/2026/03/cwsn.html",
      "thumbnail": "",
      "description": "विशेष गरजा असणारी बालके"
    },
    {
      "id": "post_48",
      "title": "सर्व समावेशक शिक्षण",
      "url": "https://www.e-gurumitra.com/2026/03/inclusive-education.html",
      "thumbnail": "",
      "description": "सर्व समावेशक शिक्षण"
    },
    {
      "id": "post_49",
      "title": "शैक्षणिक मूल्यमापन - तंत्रे व साधने",
      "url": "https://www.e-gurumitra.com/2026/03/evaluation.html",
      "thumbnail": "",
      "description": "शैक्षणिक मूल्यमापन - तंत्रे व साधने"
    },
    {
      "id": "post_50",
      "title": "शैक्षणिक धोरणे",
      "url": "https://www.e-gurumitra.com/2026/03/educational-policies.html",
      "thumbnail": "",
      "description": "शैक्षणिक धोरणे"
    },
    {
      "id": "post_51",
      "title": "महत्वाचे मानसशास्त्रज्ञ",
      "url": "https://www.e-gurumitra.com/2026/03/psychologist.html",
      "thumbnail": "",
      "description": "महत्वाचे मानसशास्त्रज्ञ"
    },
    {
      "id": "post_1a",
      "title": "घटक क्र. १: बालकांचा विकास",
      "url": "https://www.e-gurumitra.com/2025/09/child-development.html",
      "thumbnail": "",
      "description": "शारीरिक, मानसिक, भावनिक आणि सामाजिक विकास."
    },
    {
      "id": "post_2a",
      "title": "घटक क्र. २: शिकण्याची प्रक्रिया",
      "url": "https://www.e-gurumitra.com/2025/09/learning-process.html",
      "thumbnail": "",
      "description": "अध्ययनाचे विविध सिद्धांत"
    },
    {
      "id": "post_3a",
      "title": "घटक क्र. ३: व्यक्तिमत्व विकास",
      "url": "https://www.e-gurumitra.com/2025/09/personality-development.html",
      "thumbnail": "",
      "description": "व्यक्तिमत्व विकासाचे विविध सिद्धांत"
    },
    {
      "id": "post_4a",
      "title": "घटक क्र. ४: बुद्धी आणि सर्जनशीलता",
      "url": "https://www.e-gurumitra.com/2025/09/intelligence-and-creativity.html",
      "thumbnail": "",
      "description": "विविध बुद्धिमत्ता सिद्धांत"
    },
    {
      "id": "post_5a",
      "title": "घटक क्र. ५: विशेष गरजा असलेली बालके व समावेशित शिक्षण",
      "url": "https://www.e-gurumitra.com/2025/09/cwsn.html",
      "thumbnail": "",
      "description": "विशेष गरजा असणाऱ्या बालकांची ओळख"
    },
    {
      "id": "post_6a",
      "title": "घटक क्र. ६: प्रभावी अध्यापनाचा पाया",
      "url": "https://www.e-gurumitra.com/2025/09/basics-of-teaching.html",
      "thumbnail": "",
      "description": "मूलभूत संकल्पना,नियोजन"
    },
    {
      "id": "post_7a",
      "title": "घटक क्र. ७: अध्यापन पद्धती",
      "url": "https://www.e-gurumitra.com/2025/09/effective-teaching-methods.html",
      "thumbnail": "",
      "description": "प्रभावी अध्यापन पद्धती, त्यांचे फायदे."
    },
    {
      "id": "post_8a",
      "title": "घटक क्र. ८: समावेशित शिक्षण",
      "url": "https://www.e-gurumitra.com/2025/09/inclusive-education.html",
      "thumbnail": "",
      "description": "सर्व प्रकारच्या विद्यार्थ्यांना एकाच छताखाली शिक्षण"
    },
    {
      "id": "post_9a",
      "title": "घटक क्र. ९: मूल्यमापन : मूलभूत संकल्पना",
      "url": "https://www.e-gurumitra.com/2025/09/evaluation-and-tests.html",
      "thumbnail": "",
      "description": "सातत्यपूर्ण सर्वंकष मूल्यमापन"
    },
    {
      "id": "post_10a",
      "title": "घटक क्र. १०: मूल्यमापनाची साधने",
      "url": "https://www.e-gurumitra.com/2025/09/evaluation-tools.html",
      "thumbnail": "",
      "description": "साधने आणि तंत्रे, परीक्षा, निरीक्षण, प्रकल्प"
    },
    {
      "id": "post_11a",
      "title": "घटक क्र. ११: अध्यापन शास्त्रातील महत्त्वाचे मानसशास्त्रज्ञ",
      "url": "https://e-gurumitra.com/2025/09/important-psychologists-in-pedagogy.html",
      "thumbnail": "",
      "description": "मानसशास्त्रज्ञांच्या कार्याचा आणि सिद्धांतांचा परिचय"
    }
  ]
}
